SecureMessaging.py
SecureMessaging-1.0.7.dist-info/METADATA
SecureMessaging-1.0.7.dist-info/WHEEL
SecureMessaging-1.0.7.dist-info/top_level.txt
SecureMessaging-1.0.7.dist-info/RECORD
