Metadata-Version: 2.1
Name: SecureMessaging
Version: 1.0.7
Summary: Secure Messaging
Home-page: https://github.com/ethicalhacker7192/SecureMessaging
Author: Guinea_Pig_Lord
Author-email: bear@lowrey.us
License: MIT
Keywords: Secure Messaging
Platform: any
Classifier: Development Status :: 3 - Alpha
Classifier: Intended Audience :: Developers
Classifier: License :: OSI Approved :: MIT License
Classifier: Programming Language :: Python :: 3
Requires-Dist: cryptography
Requires-Dist: platform
Requires-Dist: prompt-toolkit
